ghostos_common-0.3.5.dist-info/METADATA
ghostos_common-0.3.5.dist-info/WHEEL
ghostos_common-0.3.5.dist-info/entry_points.txt
ghostos_common-0.3.5.dist-info/licenses/LICENSE
ghostos_common/__init__.py
ghostos_common/entity.py
ghostos_common/helpers/__init__.py
ghostos_common/helpers/code_analyser.py
ghostos_common/helpers/coding.py
ghostos_common/helpers/dictionary.py
ghostos_common/helpers/files.py
ghostos_common/helpers/hashes.py
ghostos_common/helpers/io.py
ghostos_common/helpers/modules.py
ghostos_common/helpers/openai.py
ghostos_common/helpers/string.py
ghostos_common/helpers/timeutils.py
ghostos_common/helpers/trans.py
ghostos_common/helpers/tree_sitter.py
ghostos_common/helpers/yaml.py
ghostos_common/identifier.py
ghostos_common/prompter.py
ghostos_common-0.3.5.dist-info/RECORD
